{
  "bakedAt": "2026-04-29T01:54:41.742Z",
  "out": "snapshots-published",
  "slugs": [
    {
      "slug": "admin-addons",
      "result": "ok",
      "bytesIn": 1182531,
      "bytesOut": 1182660,
      "tokensRemoved": {
        "sulliesbakery.com": 33,
        "Sullie's Bakery (raw)": 1
      }
    },
    {
      "slug": "admin-entries-overview",
      "result": "ok",
      "bytesIn": 1179907,
      "bytesOut": 1180096,
      "tokensRemoved": {
        "sulliesbakery.com": 48,
        "Sullie's Bakery (raw)": 1
      }
    },
    {
      "slug": "admin-entries-list",
      "result": "ok",
      "bytesIn": 1164044,
      "bytesOut": 1164161,
      "tokensRemoved": {
        "sulliesbakery.com": 32,
        "mailinator.com": 5,
        "Sullie's Bakery (raw)": 1,
        "lorem-style fixture token: \"Recusandae\"": 1
      }
    },
    {
      "slug": "admin-entry-detail",
      "result": "ok",
      "bytesIn": 1217419,
      "bytesOut": 1217503,
      "tokensRemoved": {
        "sulliesbakery.com": 20,
        "mailinator.com": 2,
        "Sullie's Bakery (raw)": 1,
        "lorem-style fixture token: \"Recusandae\"": 1
      }
    },
    {
      "slug": "admin-forms-overview",
      "result": "ok",
      "bytesIn": 1144862,
      "bytesOut": 1139540,
      "tokensRemoved": {
        "sulliesbakery.com": 35,
        "Sullie's Bakery (raw)": 1
      }
    },
    {
      "slug": "admin-payments",
      "result": "ok",
      "bytesIn": 1184062,
      "bytesOut": 1184116,
      "tokensRemoved": {
        "sulliesbakery.com": 15,
        "asdas@adsfds.com": 1,
        "Sullie's Bakery (raw)": 1
      }
    },
    {
      "slug": "admin-payment-detail",
      "result": "ok",
      "bytesIn": 1118252,
      "bytesOut": 1118236,
      "tokensRemoved": {
        "sulliesbakery.com": 8,
        "mailinator.com": 2,
        "cufutob@mailinator.com": 2,
        "Sullie's Bakery (raw)": 1,
        "lorem-style fixture token: \"veniam\"": 1
      }
    },
    {
      "slug": "admin-payments-coupons",
      "result": "ok",
      "bytesIn": 1123871,
      "bytesOut": 1123976,
      "tokensRemoved": {
        "sulliesbakery.com": 27,
        "Sullie's Bakery (raw)": 1
      }
    },
    {
      "slug": "admin-settings-access",
      "result": "ok",
      "bytesIn": 1122682,
      "bytesOut": 1122731,
      "tokensRemoved": {
        "sulliesbakery.com": 13,
        "Sullie's Bakery (raw)": 1
      }
    },
    {
      "slug": "admin-settings-email",
      "result": "ok",
      "bytesIn": 1180856,
      "bytesOut": 1180933,
      "tokensRemoved": {
        "sulliesbakery.com": 20,
        "Sullie's Bakery (raw)": 1
      }
    },
    {
      "slug": "admin-settings-general",
      "result": "ok",
      "bytesIn": 1097352,
      "bytesOut": 1097401,
      "tokensRemoved": {
        "sulliesbakery.com": 13,
        "Sullie's Bakery (raw)": 1
      }
    },
    {
      "slug": "admin-settings-geolocation",
      "result": "ok",
      "bytesIn": 1107859,
      "bytesOut": 1107908,
      "tokensRemoved": {
        "sulliesbakery.com": 13,
        "Sullie's Bakery (raw)": 1
      }
    },
    {
      "slug": "admin-settings-integrations",
      "result": "ok",
      "bytesIn": 1143399,
      "bytesOut": 1143448,
      "tokensRemoved": {
        "sulliesbakery.com": 13,
        "061.umair@gmail.com": 1,
        "Sullie's Bakery (raw)": 1
      }
    },
    {
      "slug": "admin-settings-misc",
      "result": "ok",
      "bytesIn": 1094521,
      "bytesOut": 1094574,
      "tokensRemoved": {
        "sulliesbakery.com": 14,
        "Sullie's Bakery (raw)": 1
      }
    },
    {
      "slug": "admin-settings-payments",
      "result": "ok",
      "bytesIn": 1128800,
      "bytesOut": 1128870,
      "tokensRemoved": {
        "sulliesbakery.com": 19,
        "Sullie's Bakery (raw)": 2
      }
    },
    {
      "slug": "admin-settings-validation",
      "result": "ok",
      "bytesIn": 1102864,
      "bytesOut": 1102913,
      "tokensRemoved": {
        "sulliesbakery.com": 13,
        "Sullie's Bakery (raw)": 1
      }
    },
    {
      "slug": "admin-templates",
      "result": "ok",
      "bytesIn": 5368308,
      "bytesOut": 5368389,
      "tokensRemoved": {
        "sulliesbakery.com": 21,
        "Sullie's Bakery (raw)": 1
      }
    },
    {
      "slug": "admin-tools-action-scheduler",
      "result": "ok",
      "bytesIn": 1111439,
      "bytesOut": 1111528,
      "tokensRemoved": {
        "sulliesbakery.com": 23,
        "Sullie's Bakery (raw)": 1
      }
    },
    {
      "slug": "admin-tools-export",
      "result": "ok",
      "bytesIn": 1132414,
      "bytesOut": 1132467,
      "tokensRemoved": {
        "sulliesbakery.com": 14,
        "Sullie's Bakery (raw)": 1
      }
    },
    {
      "slug": "admin-tools-import",
      "result": "ok",
      "bytesIn": 1092821,
      "bytesOut": 1092870,
      "tokensRemoved": {
        "sulliesbakery.com": 13,
        "Sullie's Bakery (raw)": 1
      }
    },
    {
      "slug": "admin-tools-logs",
      "result": "ok",
      "bytesIn": 1120335,
      "bytesOut": 1120387,
      "tokensRemoved": {
        "sulliesbakery.com": 12,
        "Sullie's Bakery (raw)": 1
      }
    },
    {
      "slug": "admin-tools-system",
      "result": "ok",
      "bytesIn": 1092132,
      "bytesOut": 1092203,
      "tokensRemoved": {
        "sulliesbakery.com": 16,
        "C:\\Users\\PC": 4,
        "Sullie's Bakery (raw)": 1
      }
    }
  ]
}